{
  "version": "1.2.0",
  "chapters": [
    {
      "startTime": 0,
      "title": "Good Morning - Heritage brands are hiring culture, not just endorsing it."
    },
    {
      "startTime": 30,
      "title": "The Lead: Stone Island builds Dave an archive exhibition. Th"
    },
    {
      "startTime": 90,
      "title": "Signal 1: Miu Miu's cool-down signals the end of irony-led l"
    },
    {
      "startTime": 114,
      "title": "Signal 2: Amazon joining Google's Universal Commerce Protoco"
    },
    {
      "startTime": 138,
      "title": "Signal 3: Faye Toogood calls design's widening audience exci"
    },
    {
      "startTime": 162,
      "title": "Signal 4: Kiko Milano enters the US through Macy's. European"
    },
    {
      "startTime": 186,
      "title": "Signal 5: L'Oréal Paris uses The Devil Wears Prada sequel as"
    },
    {
      "startTime": 225,
      "title": "The Pattern"
    },
    {
      "startTime": 270,
      "title": "Wrap Up"
    }
  ]
}