{
  "version": "1.2.0",
  "chapters": [
    {
      "startTime": 0,
      "title": "Good Morning - Brands built on hype are quietly erasing their own origins."
    },
    {
      "startTime": 30,
      "title": "The Lead: Niche fragrance growth stalls. The premiumisation "
    },
    {
      "startTime": 90,
      "title": "Signal 1: A Web3 drinks brand just quietly deleted its own f"
    },
    {
      "startTime": 114,
      "title": "Signal 2: Luxury houses spent Milan Design Week buying into "
    },
    {
      "startTime": 138,
      "title": "Signal 3: Thailand is using live-streamers to clear a nation"
    },
    {
      "startTime": 163,
      "title": "Signal 4: Brussels is forcing Google to open Gemini's Androi"
    },
    {
      "startTime": 187,
      "title": "Signal 5: Y2K visual codes are now the shorthand for gut-hea"
    },
    {
      "startTime": 226,
      "title": "The Pattern"
    },
    {
      "startTime": 271,
      "title": "Wrap Up"
    }
  ]
}